<?xml version="1.0" encoding="UTF-8"?>
<objects serializationModel="Studio.01.09.00">
    <object class="Event" id="{1539b3a5-f3bb-4bb5-bfc2-0f2fcbebbf5a}">
        <property name="name">
            <value>Reloading</value>
        </property>
        <property name="outputFormat">
            <value>2</value>
        </property>
        <relationship name="folder">
            <destination>{e8b3b379-bfe4-4b8b-8284-08d8a60eec36}</destination>
        </relationship>
        <relationship name="mixer">
            <destination>{a7f042ab-00ff-4731-bb8a-ecb49ab9e1ad}</destination>
        </relationship>
        <relationship name="masterTrack">
            <destination>{442fe170-c492-48f6-a47b-a31aa8391579}</destination>
        </relationship>
        <relationship name="mixerInput">
            <destination>{1d0754ec-9b77-4824-b328-195206458aa1}</destination>
        </relationship>
        <relationship name="automatableProperties">
            <destination>{259d4e73-3998-4cd2-a872-a9983d09aa5f}</destination>
        </relationship>
        <relationship name="markerTracks">
            <destination>{968a0a27-3369-4c09-a88c-f8abdfaf04bd}</destination>
        </relationship>
        <relationship name="groupTracks">
            <destination>{1697b4ff-f9c6-4262-8d4c-11db6b5051d1}</destination>
        </relationship>
        <relationship name="timeline">
            <destination>{fe24fead-d7bb-42ce-ad36-81dab1c7830c}</destination>
        </relationship>
        <relationship name="banks">
            <destination>{0bc9bae9-9e73-4c58-abfb-8c4c11f990b3}</destination>
        </relationship>
    </object>
    <object class="EventMixer" id="{a7f042ab-00ff-4731-bb8a-ecb49ab9e1ad}">
        <relationship name="masterBus">
            <destination>{968e3803-39b1-4cbf-9414-0061b9c5a4b9}</destination>
        </relationship>
    </object>
    <object class="MasterTrack" id="{442fe170-c492-48f6-a47b-a31aa8391579}">
        <relationship name="mixerGroup">
            <destination>{968e3803-39b1-4cbf-9414-0061b9c5a4b9}</destination>
        </relationship>
    </object>
    <object class="MixerInput" id="{1d0754ec-9b77-4824-b328-195206458aa1}">
        <relationship name="effectChain">
            <destination>{64fcca27-11d8-43fb-8e7a-4ff756862a07}</destination>
        </relationship>
        <relationship name="panner">
            <destination>{4bb9cd91-79a8-49fc-a483-67e851aae60d}</destination>
        </relationship>
        <relationship name="output">
            <destination>{63eccbe3-36d8-4252-a791-3632d315d5e8}</destination>
        </relationship>
    </object>
    <object class="EventAutomatableProperties" id="{259d4e73-3998-4cd2-a872-a9983d09aa5f}"/>
    <object class="MarkerTrack" id="{968a0a27-3369-4c09-a88c-f8abdfaf04bd}"/>
    <object class="GroupTrack" id="{1697b4ff-f9c6-4262-8d4c-11db6b5051d1}">
        <relationship name="modules">
            <destination>{0abbab51-04b0-43ce-9a4e-d6aad03290ef}</destination>
        </relationship>
        <relationship name="mixerGroup">
            <destination>{4a7145aa-9c68-4b01-8150-006b5996a866}</destination>
        </relationship>
    </object>
    <object class="Timeline" id="{fe24fead-d7bb-42ce-ad36-81dab1c7830c}">
        <relationship name="modules">
            <destination>{0abbab51-04b0-43ce-9a4e-d6aad03290ef}</destination>
        </relationship>
    </object>
    <object class="EventMixerMaster" id="{968e3803-39b1-4cbf-9414-0061b9c5a4b9}">
        <relationship name="effectChain">
            <destination>{531902f7-26d3-43d5-9dad-ad9e19dc8363}</destination>
        </relationship>
        <relationship name="panner">
            <destination>{543d22e8-5ca3-4b0e-b2d0-de3f8f4c1b54}</destination>
        </relationship>
        <relationship name="mixer">
            <destination>{a7f042ab-00ff-4731-bb8a-ecb49ab9e1ad}</destination>
        </relationship>
    </object>
    <object class="MixerBusEffectChain" id="{64fcca27-11d8-43fb-8e7a-4ff756862a07}">
        <relationship name="effects">
            <destination>{084da553-c221-4bfb-8196-4fae73f42375}</destination>
        </relationship>
    </object>
    <object class="MixerBusPanner" id="{4bb9cd91-79a8-49fc-a483-67e851aae60d}"/>
    <object class="MultiSound" id="{0abbab51-04b0-43ce-9a4e-d6aad03290ef}">
        <property name="length">
            <value>0.70000000000000007</value>
        </property>
        <relationship name="sounds">
            <destination>{18796dfd-1834-4eea-b8ea-f6f2a4e868d2}</destination>
            <destination>{0d9794af-717f-4967-bf0f-3757246eec47}</destination>
            <destination>{a312d85e-3960-45f4-a259-9580e1783df3}</destination>
        </relationship>
    </object>
    <object class="EventMixerGroup" id="{4a7145aa-9c68-4b01-8150-006b5996a866}">
        <property name="name">
            <value>Audio 1</value>
        </property>
        <relationship name="effectChain">
            <destination>{6fe186c6-0350-43e8-bda0-407c072af913}</destination>
        </relationship>
        <relationship name="panner">
            <destination>{71b64dd1-8422-4419-bd5d-26224ac84c6e}</destination>
        </relationship>
        <relationship name="output">
            <destination>{968e3803-39b1-4cbf-9414-0061b9c5a4b9}</destination>
        </relationship>
    </object>
    <object class="MixerBusEffectChain" id="{531902f7-26d3-43d5-9dad-ad9e19dc8363}">
        <relationship name="effects">
            <destination>{9759499e-6be7-4444-85bd-9a71951f4a87}</destination>
            <destination>{80edeec9-1a5d-45f0-91af-8c934257b1f1}</destination>
        </relationship>
    </object>
    <object class="MixerBusPanner" id="{543d22e8-5ca3-4b0e-b2d0-de3f8f4c1b54}"/>
    <object class="MixerBusFader" id="{084da553-c221-4bfb-8196-4fae73f42375}"/>
    <object class="SingleSound" id="{18796dfd-1834-4eea-b8ea-f6f2a4e868d2}">
        <relationship name="audioFile">
            <destination>{d8a2f0ae-9f67-4f26-ad50-03b9daafcb9d}</destination>
        </relationship>
    </object>
    <object class="SingleSound" id="{0d9794af-717f-4967-bf0f-3757246eec47}">
        <relationship name="audioFile">
            <destination>{0216fb25-6564-4fc9-8640-398051f060f2}</destination>
        </relationship>
    </object>
    <object class="SingleSound" id="{a312d85e-3960-45f4-a259-9580e1783df3}">
        <relationship name="audioFile">
            <destination>{d4cfad94-df05-426e-8113-fdd655bfeead}</destination>
        </relationship>
    </object>
    <object class="MixerBusEffectChain" id="{6fe186c6-0350-43e8-bda0-407c072af913}">
        <relationship name="effects">
            <destination>{8886cc64-bcf2-4650-b630-007a2aac48cb}</destination>
        </relationship>
    </object>
    <object class="MixerBusPanner" id="{71b64dd1-8422-4419-bd5d-26224ac84c6e}"/>
    <object class="MixerBusFader" id="{9759499e-6be7-4444-85bd-9a71951f4a87}"/>
    <object class="SpatialiserEffect" id="{80edeec9-1a5d-45f0-91af-8c934257b1f1}"/>
    <object class="MixerBusFader" id="{8886cc64-bcf2-4650-b630-007a2aac48cb}"/>
</objects>
